README.md
setup.py
ay/Canvas.py
ay/Layout.py
ay/__init__.py
ay.egg-info/PKG-INFO
ay.egg-info/SOURCES.txt
ay.egg-info/dependency_links.txt
ay.egg-info/requires.txt
ay.egg-info/top_level.txt