Metadata-Version: 1.2
Name: ay
Version: 0.1.1
Summary: Tiny framework for generative art using Python
Home-page: https://github.com/rubenafo/ay
Author: Ruben Afonso
Author-email: rbfrancos@gmail.com
License: UNKNOWN
Keywords: generative art,cairo,generative,python,design
Platform: UNKNOWN
Classifier: Programming Language :: Python :: 3
Classifier: License :: OSI Approved :: MIT License
Classifier: Operating System :: OS Independent
Requires-Python: >=3.6
